{
    "piped": [],
    "hls": [],
    "proxy": [],
    "invidious": [
        "https://yt.omada.cafe",
        "https://invidious.nikkosphere.com",
        "https://invidious.baczek.me",
        "https://y.com.sb",
        "https://iv.melmac.space",
        "https://inv.vern.cc",
        "https://lekker.gay",
        "https://iv.duti.dev",
        "https://invidious.reallyaweso.me",
        "https://yt.omada.cafe"
    ],
    "hyperpipe": [
        "https://hyperpipeapi.darkness.services",
        "https://hyperpipebackend.in.projectsegfau.lt",
        "https://hyperpipeapi.ducks.party",
        "https://hyperpipeapi.onrender.com"
    ],
    "jiosaavn": "https://jiosavan-ytify.vercel.app",
    "health": "I"
}