{
    "piped": [
        "https://api.piped.private.coffee"
    ],
    "hls": [],
    "proxy": [],
    "invidious": [
        "https://yt.omada.cafe",
        "https://invidious.reallyaweso.me",
        "https://invidious.nikkosphere.com",
        "https://inv.vern.cc",
        "https://iv.melmac.space",
        "https://yt.omada.cafe",
        "https://y.com.sb"
    ],
    "hyperpipe": [
        "https://hyperpipeapi.darkness.services",
        "https://hyperpipeapi.onrender.com",
        "https://hyperpipebackend.in.projectsegfau.lt",
        "https://hyperpipeapi.ducks.party"
    ],
    "jiosaavn": "https://saavn-sigma.vercel.app",
    "health": "I"
}